{
    "type": "FeatureCollection",
    "generator": "smartcity",
    "copyright": "Smartcity",
    "timestamp": "2021-05-27T09:28:58Z",
    "features": [
        {
            "type": "Feature",
            "properties": {
                "Building name": "Bậc tam cấp của tòa nhà giữa Ngọ Môn",
                "height": 4.64,
                "color": "#723a2d",
                "idb": "1"
            },
            "geometry": {
                "type": "MultiPolygon",
                "coordinates": [
                    [
                        [
                            [107.57910655514502,16.46778194301068,5.04],
                            [107.57913533994103,16.46780208985584,5.04],
                            [107.57913699851765,16.467799910591058,5.04],
                            [107.57910821372153,16.467779763745902,5.04]
                        ]
                    ],
                    [
                        [
                            [107.57910821372153,16.467779763745902,5.28],
                            [107.57913699851765,16.467799910591047,5.28],
                            [107.57913865709428,16.467797731326243,5.28],
                            [107.57910987229793,16.467777584481084,5.28]
                        ]
                    ],
                    [
                        [
                            [107.57910987229805,16.467777584481123,5.52],
                            [107.57913865709439,16.467797731326282,5.52],
                            [107.579140315671,16.46779555206149,5.52],
                            [107.57911153087447,16.467775405216337,5.52]
                        ]
                    ],
                    [
                        [
                            [107.57911153087447,16.467775405216344,5.76],
                            [107.579140315671,16.46779555206147,5.76],
                            [107.57914197424762,16.467793372796685,5.76],
                            [107.57911318945088,16.467773225951536,5.76]
                        ]
                    ]
                ]
            },
            "id": "pp1"
        }
    ]
}