{
    "type": "FeatureCollection",
    "generator": "smartcity",
    "copyright": "Smartcity",
    "timestamp": "2021-05-27T09:28:58Z",
    "features": [
        {
            "type": "Feature",
            "properties": {
                "Building name": "Chân lan can tường phải",
                "height": 0.3,
                "color": "#838b94",
                "idb": "1"
            },
            "geometry": {
                "type": "Polygon",
                "coordinates": [
                    [
                        [107.5794619999435,16.467786000071776,4.64],
                        [107.57945975458263,16.467784374492137,4.64],
                        [107.57933040085561,16.467948688691596,4.64],
                        [107.5793326462184,16.467950314271235,4.64]
                    ]
                ]
            },
            "id": "pp1"
        }
    ]
}